<?xml version="1.0" encoding="utf-8"?>
<!-- Example format for catalogue files. -->
<catalogue xml:lang="en">
  <message key="texts">Info</message>
  <message key="inscriptions">Inscriptions</message>
  <message key="catalogue">Catalogue</message>
  <message key="search">Search</message>
  <message key="admin">Admin</message>
  <message key="language">Language</message>
  <message key="indices">Indices</message>
  <message key="person_name">Personal names</message>
  <message key="persons">Prosopography</message>
  <message key="mentioned_places">Places</message>
  <message key="institutions">Institutions</message>
  <message key="divinities">Divinities</message>
  <message key="lemmata">Lemmata</message>
  <message key="menu-language">Language</message>
  <message key="places">Political entities</message>
  <message key="foreword">About the project</message>
  <message key="the_inscriptions">Inscriptions</message>
  <message key="political_entities">Political entities</message>
  <message key="the_institutions">Institutions</message>
  <message key="a_complex_mosaic">A complex mosaic</message>
  <message key="research_overview_and_prospects">Research overview and prospects</message>
  <message key="literary_sources">Literary sources</message>
  <message key="bibliographic_references">Bibliographic references</message>
  <message key="site_description">A collection of the epigraphic records pertaining to the Cretan institutions of the period between VII and I century BC, with insights into the political realities of Crete and their institutions</message>
  <message key="facet-bibliographic_reference">Bibliographic reference</message>
  <message key="facet-period">Period</message>
  <message key="facet-area">Area</message>
  <message key="facet-provenance">Provenance</message>
  <message key="facet-current_location">Current location</message>
  <message key="facet-inscription_type">Inscription type</message>
  <message key="facet-support_type">Support type</message>
  <message key="facet-mentioned_places">Mentioned places</message>
  <message key="facet-mentioned_divinities">Mentioned divinities</message>
  <message key="facet-mentioned_institutions">Mentioned institutions</message>
  <message key="facet-type_of_mentioned_institutions">Type of mentioned institutions</message>
  <message key="facet-sphere_or_role_of_mentioned_institutions">Sphere or role of mentioned institutions</message>
</catalogue>
